revit_mcp-0.5.15.dist-info/licenses/LICENSE
xml_revit_mcp/__init__.py
xml_revit_mcp/prompts.py
xml_revit_mcp/resources.py
xml_revit_mcp/revit_connection.py
xml_revit_mcp/rpc.py
xml_revit_mcp/server.py
xml_revit_mcp/tools.py
revit_mcp-0.5.15.dist-info/METADATA
revit_mcp-0.5.15.dist-info/WHEEL
revit_mcp-0.5.15.dist-info/entry_points.txt
revit_mcp-0.5.15.dist-info/top_level.txt
revit_mcp-0.5.15.dist-info/RECORD
